logger_app.py
alfaslogger-0.1.6.dist-info/METADATA
alfaslogger-0.1.6.dist-info/WHEEL
alfaslogger-0.1.6.dist-info/top_level.txt
alfaslogger-0.1.6.dist-info/RECORD
