Metadata-Version: 2.1
Name: alfaslogger
Version: 0.1.6
Summary: Web GUI destekli Alfaslogger paketi
Home-page: https://github.com/TheAlfa31
Author: TcAlfa31
Author-email: sosyalfaone@gmail.com
Classifier: Programming Language :: Python :: 3
Classifier: License :: OSI Approved :: MIT License
Classifier: Operating System :: OS Independent
Requires-Python: >=3.7
Requires-Dist: websockets>=10.0
